{
  "function": {
    "name": "ChangePsw",
    "namespace": "TcHmi.Functions.TcHmiProject1",
    "displayName": "ChangePsw",
    "description": "",
    "waitMode": "Synchronous",
    "category": "",
    "returnValue": {
      "type": "tchmi:general#/definitions/String"
    },
    "visible": true,
    "injectContextObject": false,
    "arguments": [
      {
        "name": "user",
        "displayName": "username",
        "type": "tchmi:general#/definitions/String",
        "description": "This is an important Parameter which does... This text is used in a tooltip.",
        "defaultValue": "",
        "required": true,
        "bindable": true,
        "restParameter": false,
        "asReference": false,
        "allowControlAttributeBindingOptions": false
      },
      {
        "name": "password",
        "displayName": "password",
        "type": "tchmi:general#/definitions/String",
        "description": "",
        "defaultValue": "",
        "required": true,
        "bindable": true,
        "restParameter": false,
        "asReference": false,
        "allowControlAttributeBindingOptions": false
      }
    ]
  },
  "$schema": "../.hmiframework/Schema/FunctionDescription.Schema.json"
}